LICENSE
MANIFEST.in
README.rst
funconfthree.py
setup.cfg
setup.py
funconfthree.egg-info/PKG-INFO
funconfthree.egg-info/SOURCES.txt
funconfthree.egg-info/dependency_links.txt
funconfthree.egg-info/requires.txt
funconfthree.egg-info/top_level.txt
tests/__init__.py
tests/test_config.py
tests/test_decorators.py